rocinet/__init__.py
rocinet/rocinet.py
rocinet/enum/__init__.py
rocinet/enum/dataset_type.py
rocinet/model/__init__.py
rocinet/model/base_object.py
rocinet/model/code_base_object.py
rocinet/model/data_item.py
rocinet/model/dataset.py
rocinet/model/dataset_type.py
rocinet/utils/__init__.py
rocinet/utils/content_loader.py
rocinet-0.4.0.dist-info/licenses/licence.txt
rocinet-0.4.0.dist-info/METADATA
rocinet-0.4.0.dist-info/WHEEL
rocinet-0.4.0.dist-info/top_level.txt
rocinet-0.4.0.dist-info/RECORD
