Metadata-Version: 2.4
Name: rocinet
Version: 0.4.0
Summary: Rocinet SDK package for Python
Author-email: Michal Bartl <michal.bartl@gmail.com>
License: WTFPL
License-File: licence.txt
Requires-Dist: requests
Dynamic: license-file
